zubanls/__init__.py
zubanls-0.0.2.dist-info/METADATA
zubanls-0.0.2.dist-info/WHEEL
zubanls-0.0.2.dist-info/top_level.txt
zubanls-0.0.2.dist-info/RECORD
