Metadata-Version: 2.1
Name: zubanls
Version: 0.0.2
Summary: Alias for ZubanLS - use pip install zuban instead
Home-page: https://github.com/zubanls/zuban
Author: David Halter
Author-email: info@zubanls.com
Maintainer: David Halter
Maintainer-email: info@zubanls.com
License: Proprietary
Keywords: typechecking mypy static analysis autocompletion
Platform: UNKNOWN
Classifier: Development Status :: 1 - Planning
Classifier: Environment :: Plugins
Classifier: Intended Audience :: Developers
Classifier: License :: Other/Proprietary License
Classifier: Programming Language :: Python :: 3
Classifier: Topic :: Software Development :: Libraries :: Python Modules
Classifier: Topic :: Text Editors :: Integrated Development Environments (IDE)
Classifier: Topic :: Utilities
Classifier: Typing :: Typed
Requires-Python: >=3.4
Requires-Dist: zubanls (<0.1.0,>=0.0.0)
